i3_resurrect/__init__.py
i3_resurrect/config.py
i3_resurrect/layout.py
i3_resurrect/main.py
i3_resurrect/programs.py
i3_resurrect/treeutils.py
i3_resurrect/util.py
i3_resurrect-1.4.5.dist-info/LICENSE
i3_resurrect-1.4.5.dist-info/METADATA
i3_resurrect-1.4.5.dist-info/WHEEL
i3_resurrect-1.4.5.dist-info/entry_points.txt
i3_resurrect-1.4.5.dist-info/top_level.txt
i3_resurrect-1.4.5.dist-info/RECORD
