Metadata-Version: 2.1
Name: i3-resurrect
Version: 1.4.5
Summary: A simple but flexible solution to saving and restoring i3 workspace layouts
Home-page: https://github.com/JonnyHaystack/i3-resurrect
Author: Jonathan Haylett
Author-email: jonathan@haylett.dev
License: GNU GPL Version 3
Platform: UNKNOWN
Classifier: Programming Language :: Python :: 3
Classifier: License :: OSI Approved :: GNU General Public License v3 (GPLv3)
Classifier: Operating System :: POSIX :: Linux
Requires-Python: >=3.6
License-File: LICENSE
Requires-Dist: Click
Requires-Dist: i3ipc
Requires-Dist: natsort
Requires-Dist: psutil
